execution_unit.v
/*
 Northwestern University
 CompEng361 - Fall 2023
 Lab 1
 
 Name: Ben Ferreira
 NetID: bpf2734
 
 */

module ExecutionUnit(out, opA, opB, func, auxFunc);
  output [31:0] out;
  input [31:0]  opA, opB;
  input [2:0] 	 func;
  input [6:0] 	 auxFunc;

  // Place your code here
  reg [31:0] myOutput;
  wire signed [31:0] signedopA = $signed(opA);
  wire signed [31:0] signedopB = $signed(opB);
  reg enable = 1'b0;
  wire [31:0] mul_out;
  Booth_multiplication booth1(signedopA, signedopB, mul_out, enable);

  always @(*)
  begin
    //check each bit of the input to classify them
    // enable = 1'b0;
    case (func[2:0])
      //Arithmetic
      3'b000:
        if (auxFunc[5] == 1'b1)
        begin
          myOutput = opA - opB;
        end
        else if (auxFunc[0] == 1'b1)
        begin
          enable = 1'b1;
        end
        else
        begin
          myOutput = opA + opB;
        end

      //SRL and SRA
      3'b101:
        if (auxFunc[5] == 1'b1)
        begin
          myOutput = signedopA >>> signedopB;
        end
        else
        begin
          myOutput = opA >> opB;
        end
      3'b001:
        myOutput = opA << opB;
      3'b010:
        myOutput = 1 ? signedopA < signedopB : 0;
      3'b011:
        myOutput = 1 ? opA < opB : 0;
      3'b100:
        myOutput = opA ^ opB;
      3'b110:
        myOutput = opA | opB;
      3'b111:
        myOutput = opA & opB;
      default:
        myOutput = 32'b0;
    endcase
  end
  assign out = enable ? mul_out :  myOutput ;
endmodule // ExecutionUnit


module Booth_multiplication (signedopA, signedopB, out, enable);

  input signed [31:0] signedopA, signedopB;
  input enable;
  output signed [31:0] out;
  reg [31:0] out_result;
  reg [64:0] accumulator = 64'b0;
  reg [64:0] addition_val;
  reg signed sign;
  reg signed [31:0] cmpval;
  integer i;

  assign out = accumulator[31:0];
  always @(*) begin
      if (enable == 1'b1) begin
        addition_val = {signedopA, {32'b0}};
        for (i = 0; i < 32; i = i + 1) begin
            sign = accumulator[63];
            cmpval = signedopB[i-1];
            if (i == 1'b0) begin
              cmpval = 32'b0;
            end
            if (signedopB[i] == 1'b0 && cmpval == 1'b0) begin
              accumulator = accumulator + 1'b0;
            end
            else if (signedopB[i] == 1'b0 && cmpval == 1'b1) begin
              accumulator = accumulator + addition_val;
            end
            else if (signedopB[i] == 1'b1 && cmpval == 1'b0) begin 
              accumulator = accumulator - addition_val;
            end 
            else if (signedopB[i] == 1'b1 && cmpval == 1'b1) begin 
              accumulator = accumulator + 1'b0;
            end 

            accumulator = accumulator >> 1;
            accumulator[63] = sign;  
        end
        //sign = accumulator[31];
        // accumulator = accumulator >> 1;
        $display("answer is %8x", accumulator);
        //accumulator[31] = sign; 
      end
  end 



endmodule

lab1_test.v
`include "execution_unit.v"
module ExecutionUnit_tb;

    // Inputs
    reg [31:0] opA, opB;
    reg [2:0] func;
    reg [6:0] auxFunc;
    
    // Output
    wire [31:0] out;

    // Instantiate the ExecutionUnit module
    ExecutionUnit UUT (
        .out(out),
        .opA(opA),
        .opB(opB),
        .func(func),
        .auxFunc(auxFunc)
    );

    // Clock generation
    reg clk = 0;
    always #5 clk = ~clk;

    // Testbench stimulus
    initial begin
        $dumpfile("ExecutionUnit_tb.vcd");
        $dumpvars(0, ExecutionUnit_tb);
        
        // Test Case 1: Addition (func=000, auxFunc[5]=0)
        opA = 10;
        opB = 5;
        func = 3'b000;
        auxFunc = 7'b0000000;
        #10;
        if (out !== 15) $display("Test Case 1 Failed");
        
        // Test Case 1.5: Subtraction (func=000, auxFunc[5]=1)
        opA = 10;
        opB = 5;
        func = 3'b000;
        auxFunc = 7'b0100000;
        #10;
	if (out !== 5) $display("Subtraction Failed");

        // Test Case 2: SLL (func=001)
        opA = 8;
        opB = 2;
        func = 3'b001;
        #10;
        if (out !== 32) $display("Test Case 2 Failed");

        // Test Case 3: SRA (func=101, auxFunc[5]=1)
        opA = -20;
        opB = 1;
        func = 3'b101;
        auxFunc = 7'b0100000;
        #20;
        if (out !== -10) $display("Test Case 3 Failed");
        
        // Test Case 3: SRL (func=101, auxFunc[5]=0)
	opA = 16;
        opB = 2;
        func = 3'b101;
        auxFunc = 7'b0000000;
        #10;
        if (out !== 4) $display("Logical shit right Failed");


        // Test Case 4: AND (func=111)
        opA = 5;
        opB = 3;
        func = 3'b111;
        #10;
        if (out !== 1) $display("Test Case 4 Failed");

        // Test Case 5: XOR (func=100)
        opA = 5;
        opB = 3;
        func = 3'b100;
        #10;
        if (out !== 6) $display("Test Case 5 Failed");
        
        // Test Case 6: OR (func=110)
        opA = 5;
        opB = 3;
        func = 3'b110;
        #10;
        if (out !== 7) $display("Test Case 6 Failed");

        // Test Case 7: SLT (func=010)
        opA = 5;
        opB = 8;
        func = 3'b010;
        #10;
        if (out !== 1) $display("Test Case 7 Failed");

     // Test Case 7.5: SLT (func=010)
        opA = -5;
        opB = -8;
        func = 3'b010;
        #10;
	if (out !== 0) $display("signed comparison Failed");

        
        // Test Case 8: SLTU (func=011)
        opA = -5;
        opB = -8;
        func = 3'b011;
        #10;
        if (out !== 0) $display("Test Case 8 Failed");

    // Test Case 9: MUL (func=011)
        opA = 8;
        opB = 3;
        func = 3'b000;
        auxFunc = 7'b1;
        #100;
        //if (out !== 0) $display("Test Case 9 Failed");


        $finish;
    end

    always begin
        #1 clk = ~clk;
    end
endmodule

ExecutionUnit_tb.vcd
$date
	Thu Jan 18 18:57:14 2024
$end
$version
	Icarus Verilog
$end
$timescale
	1s
$end
$scope module ExecutionUnit_tb $end
$var wire 32 ! out [31:0] $end
$var reg 7 " auxFunc [6:0] $end
$var reg 1 # clk $end
$var reg 3 $ func [2:0] $end
$var reg 32 % opA [31:0] $end
$var reg 32 & opB [31:0] $end
$scope module UUT $end
$var wire 7 ' auxFunc [6:0] $end
$var wire 3 ( func [2:0] $end
$var wire 32 ) opA [31:0] $end
$var wire 32 * opB [31:0] $end
$var wire 32 + signedopA [31:0] $end
$var wire 32 , signedopB [31:0] $end
$var wire 32 - out [31:0] $end
$var wire 32 . mul_out [31:0] $end
$var reg 1 / enable $end
$var reg 32 0 myOutput [31:0] $end
$scope module booth1 $end
$var wire 1 / enable $end
$var wire 32 1 signedopA [31:0] $end
$var wire 32 2 signedopB [31:0] $end
$var wire 32 3 out [31:0] $end
$var reg 65 4 accumulator [64:0] $end
$var reg 65 5 addition_val [64:0] $end
$var reg 32 6 cmpval [31:0] $end
$var reg 1 7 sign $end
$var integer 32 8 i [31:0] $end
$upscope $end
$upscope $end
$upscope $end
$enddefinitions $end
$comment Show the parameter values. $end
$dumpall
$end
#0
$dumpvars
bx 8
x7
bx 6
bx 5
b0 4
b0 3
b101 2
b1010 1
b1111 0
0/
b0 .
b1111 -
b101 ,
b1010 +
b101 *
b1010 )
b0 (
b0 '
b101 &
b1010 %
b0 $
0#
b0 "
b1111 !
$end
#1
1#
#2
0#
#3
1#
#4
0#
#5
0#
#6
1#
#7
0#
#8
1#
#9
0#
#10
b101 !
b101 -
b101 0
0#
b100000 "
b100000 '
#11
1#
#12
0#
#13
1#
#14
0#
#15
0#
#16
1#
#17
0#
#18
1#
#19
0#
#20
b100000 !
b100000 -
b100000 0
0#
b1 $
b1 (
b10 ,
b10 2
b10 &
b10 *
b1000 +
b1000 1
b1000 %
b1000 )
#21
1#
#22
0#
#23
1#
#24
0#
#25
0#
#26
1#
#27
0#
#28
1#
#29
0#
#30
b11111111111111111111111111110110 !
b11111111111111111111111111110110 -
b11111111111111111111111111110110 0
0#
b101 $
b101 (
b1 ,
b1 2
b1 &
b1 *
b11111111111111111111111111101100 +
b11111111111111111111111111101100 1
b11111111111111111111111111101100 %
b11111111111111111111111111101100 )
#31
1#
#32
0#
#33
1#
#34
0#
#35
0#
#36
1#
#37
0#
#38
1#
#39
0#
#40
0#
#41
1#
#42
0#
#43
1#
#44
0#
#45
0#
#46
1#
#47
0#
#48
1#
#49
0#
#50
b100 !
b100 -
b100 0
0#
b0 "
b0 '
b10 ,
b10 2
b10 &
b10 *
b10000 +
b10000 1
b10000 %
b10000 )
#51
1#
#52
0#
#53
1#
#54
0#
#55
0#
#56
1#
#57
0#
#58
1#
#59
0#
#60
b1 !
b1 -
b1 0
0#
b111 $
b111 (
b11 ,
b11 2
b11 &
b11 *
b101 +
b101 1
b101 %
b101 )
#61
1#
#62
0#
#63
1#
#64
0#
#65
0#
#66
1#
#67
0#
#68
1#
#69
0#
#70
b110 !
b110 -
b110 0
0#
b100 $
b100 (
#71
1#
#72
0#
#73
1#
#74
0#
#75
0#
#76
1#
#77
0#
#78
1#
#79
0#
#80
b111 !
b111 -
b111 0
0#
b110 $
b110 (
#81
1#
#82
0#
#83
1#
#84
0#
#85
0#
#86
1#
#87
0#
#88
1#
#89
0#
#90
b1 !
b1 -
b1 0
0#
b10 $
b10 (
b1000 ,
b1000 2
b1000 &
b1000 *
#91
1#
#92
0#
#93
1#
#94
0#
#95
0#
#96
1#
#97
0#
#98
1#
#99
0#
#100
b0 !
b0 -
b0 0
0#
b11111111111111111111111111111000 ,
b11111111111111111111111111111000 2
b11111111111111111111111111111000 &
b11111111111111111111111111111000 *
b11111111111111111111111111111011 +
b11111111111111111111111111111011 1
b11111111111111111111111111111011 %
b11111111111111111111111111111011 )
#101
1#
#102
0#
#103
1#
#104
0#
#105
0#
#106
1#
#107
0#
#108
1#
#109
0#
#110
0#
b11 $
b11 (
#111
1#
#112
0#
#113
1#
#114
0#
#115
0#
#116
1#
#117
0#
#118
1#
#119
0#
#120
b11000 !
b11000 -
b11000 .
b11000 3
b100000000000000000000000000011000 4
b0 6
07
b100000 8
b100000000000000000000000000000000000 5
1/
0#
b1 "
b1 '
b0 $
b0 (
b11 ,
b11 2
b11 &
b11 *
b1000 +
b1000 1
b1000 %
b1000 )
